{
  "_format": "hh-sol-cache-2",
  "files": {
    "D:\\Voting Dapp\\hardhat\\contracts\\Voting.sol": {
      "lastModificationDate": 1699385384272,
      "contentHash": "178fb7fd0771ac8cd46925038f240b07",
      "sourceName": "contracts/Voting.sol",
      "solcConfig": {
        "version": "0.8.19",
        "settings": {
          "optimizer": {
            "enabled": false,
            "runs": 200
          },
          "outputSelection": {
            "*": {
              "*": [
                "abi",
                "evm.bytecode",
                "evm.deployedBytecode",
                "evm.methodIdentifiers",
                "metadata"
              ],
              "": [
                "ast"
              ]
            }
          }
        }
      },
      "imports": [],
      "versionPragmas": [
        "^0.8.2"
      ],
      "artifacts": [
        "Voting"
      ]
    }
  }
}
